README.md
setup.py
cloudrangalabs1.egg-info/PKG-INFO
cloudrangalabs1.egg-info/SOURCES.txt
cloudrangalabs1.egg-info/dependency_links.txt
cloudrangalabs1.egg-info/entry_points.txt
cloudrangalabs1.egg-info/requires.txt
cloudrangalabs1.egg-info/top_level.txt
src/__init__.py
src/logic.py
src/main.py