Metadata-Version: 2.1
Name: cloudrangalabs1
Version: 0.0.1
Summary: An application that informs you of the time in different locations and timezones
Home-page: https://www.youtube.com/channel/UCv9MUffHWyo2GgLIDLVu0KQ
Author: Ranga Wanigathunga
Author-email: prwanigathunga@gmail.com
License: UNKNOWN
Platform: UNKNOWN
Classifier: Programming Language :: Python :: 3
Classifier: License :: OSI Approved :: MIT License
Classifier: Operating System :: OS Independent
